zjwbox/__init__.py
zjwbox/auto_req.py
zjwbox/auto_sel.py
zjwbox/comm_req.py
zjwbox/pre_deal.py
zjwbox/store.py
zjwbox/update.py
zjwbox/zjwbox.py
zjwbox/boxtools/__init__.py
zjwbox/boxtools/alert_exit.py
zjwbox/boxtools/check_url.py
zjwbox/boxtools/get_session.py
zjwbox/boxtools/log_set.py
zjwbox/boxtools/proof.py
zjwbox/boxtools/proxyShop.py
zjwbox/boxtools/time_delay.py
zjwbox/encrypt/__init__.py
zjwbox/encrypt/login_all.py
zjwbox-0.3.5.dist-info/LICENSE
zjwbox-0.3.5.dist-info/METADATA
zjwbox-0.3.5.dist-info/WHEEL
zjwbox-0.3.5.dist-info/top_level.txt
zjwbox-0.3.5.dist-info/RECORD
