Metadata-Version: 2.1
Name: zjwbox
Version: 0.3.5
Summary: a box for package
Home-page: https://zjw.show
Author: zjw
Author-email: 2415528031@qq.com
License: UNKNOWN
Platform: UNKNOWN
Classifier: License :: OSI Approved :: MIT License
Classifier: Programming Language :: Python
Classifier: Intended Audience :: Developers
Classifier: Operating System :: OS Independent
Requires-Dist: wheel
Requires-Dist: wget (==3.2)
Requires-Dist: lxml (==4.6.1)
Requires-Dist: eventlet (==0.29.1)
Requires-Dist: dataclasses
Requires-Dist: pyppeteer
Requires-Dist: selenium
Requires-Dist: nest-asyncio (==1.4.1)
Requires-Dist: parsel
Requires-Dist: requests
Requires-Dist: faker
Requires-Dist: openpyxl
Requires-Dist: pymongo
Requires-Dist: pymysql
Requires-Dist: redis
Requires-Dist: jsonpath
Requires-Dist: pandas
Requires-Dist: numpy
Requires-Dist: aiohttp
Requires-Dist: psutil
Requires-Dist: fake-useragent
Requires-Dist: pyquery
Requires-Dist: DecryptLogin
